MANIFEST.in
README.md
setup.py
bin/dss-gui
bin/dss-shell
dss/__init__.py
dss/cmdApplication.py
dss/dss.py
dss/dss_gui.bat
dss/dss_gui.sh
dss/dss_shell.bat
dss/dss_shell.py
dss/gui.py
dss/interfaces.py
dss/run.bat
dss/testCore.py
dss.egg-info/PKG-INFO
dss.egg-info/SOURCES.txt
dss.egg-info/dependency_links.txt
dss.egg-info/not-zip-safe
dss.egg-info/requires.txt
dss.egg-info/top_level.txt
dss/Config/Interfaces.py
dss/Config/LoaderExample.py
dss/Config/Playground.py
dss/Config/Runner.py
dss/Config/Test.py
dss/Config/__init__.py
dss/Config/Controller/CoreController.py
dss/Config/Controller/PluginController.py
dss/Config/Controller/__init__.py
dss/Config/Model/__init__.py
dss/Config/Model/Core/Default.py
dss/Config/Model/Core/__init__.py
dss/Config/Model/Plugin/Default.py
dss/Config/Model/Plugin/IPConfig.py
dss/Config/Model/Plugin/ManualScreenShot.py
dss/Config/Model/Plugin/NMap.py
dss/Config/Model/Plugin/NetScanner.py
dss/Config/Model/Plugin/NetStat.py
dss/Config/Model/Plugin/PyKeyLogger.py
dss/Config/Model/Plugin/TShark.py
dss/Config/Model/Plugin/__init__.py
dss/Config/View/RemoveFields.py
dss/Config/View/__init__.py
dss/Config/View/Core/AddEntryView.py
dss/Config/View/Core/AddOptionsView.py
dss/Config/View/Core/DynamicView.py
dss/Config/View/Core/MasterView.py
dss/Config/View/Core/RemoveConfigurationView.py
dss/Config/View/Core/__init__.py
dss/Config/View/Plugin/AddEntryView.py
dss/Config/View/Plugin/AddOptionsView.py
dss/Config/View/Plugin/AddToBlacklistView.py
dss/Config/View/Plugin/DynamicView.py
dss/Config/View/Plugin/MasterView.py
dss/Config/View/Plugin/RemoveConfigurationView.py
dss/Config/View/Plugin/RemoveFromBlacklistView.py
dss/Config/View/Plugin/__init__.py
dss/GUI/__init__.py
dss/GUI/dss_gui.py
dss/GUI/hide.png
dss/GUI/json.png
dss/GUI/open.png
dss/GUI/pause.png
dss/GUI/screenshot.png
dss/GUI/start.png
dss/GUI/status_icon.py
dss/GUI/stop.png
dss/cli/__init__.py
dss/core/__init__.py
dss/core/config.json
dss/core/config_hardcoded.json
dss/core/core.py
dss/core/plugin.py
dss/core/archiver/Archiver.py
dss/core/archiver/__init__.py
dss/core/archiver/tarFormat.py
dss/core/archiver/zipFormat.py
