Metadata-Version: 1.1
Name: dss
Version: 0.8
Summary: Defense Support System
Home-page: https://github.com/ostrovskis/core
Author: UTEP Software Engineering Practicum Summer 2016
Author-email: UNKNOWN
License: MIT
Keywords: dss defense support system security logging archiving monitoring plugin architecture
Platform: UNKNOWN
Classifier: Development Status :: 3 - Alpha
Classifier: License :: OSI Approved :: MIT License
Classifier: Programming Language :: Python :: 2.7
Classifier: Natural Language :: English
Classifier: Topic :: Security
Classifier: Topic :: System :: Logging
Classifier: Topic :: System :: Archiving
Classifier: Topic :: System :: Monitoring
Classifier: Environment :: Plugins
